pytorchvis/__init__.py
pytorchvis/visualize_layers.py
pytorchvis-0.0.4.dist-info/LICENSE
pytorchvis-0.0.4.dist-info/METADATA
pytorchvis-0.0.4.dist-info/WHEEL
pytorchvis-0.0.4.dist-info/top_level.txt
pytorchvis-0.0.4.dist-info/RECORD
